promptscope/.gitignore
promptscope/__init__.py
promptscope/cli/__init__.py
promptscope/cli/diff.py
promptscope/cli/export.py
promptscope/cli/main.py
promptscope/cli/replay.py
promptscope/cli/stats.py
promptscope/config.py
promptscope/core/__init__.py
promptscope/core/cost.py
promptscope/core/diffing.py
promptscope/core/explain.py
promptscope/core/linter.py
promptscope/core/policies.py
promptscope/core/redaction.py
promptscope/core/replay.py
promptscope/core/scoring.py
promptscope/core/tracker.py
promptscope/core/versioning.py
promptscope/models/__init__.py
promptscope/models/diff.py
promptscope/models/events.py
promptscope/models/metrics.py
promptscope/models/output.py
promptscope/models/prompt.py
promptscope/models/replay.py
promptscope/openai.py
promptscope/sdk/__init__.py
promptscope/sdk/adapters.py
promptscope/sdk/client.py
promptscope/sdk/decorators.py
promptscope/storage/__init__.py
promptscope/storage/base.py
promptscope/storage/remote.py
promptscope/storage/sqlite.py
promptscope/telemetry.py
promptscope/utils/__init__.py
promptscope/utils/hashing.py
promptscope/utils/serialization.py
promptscope/utils/time.py
promptscope/version.py
promptscope-0.1.1.dist-info/METADATA
promptscope-0.1.1.dist-info/WHEEL
promptscope-0.1.1.dist-info/entry_points.txt
promptscope-0.1.1.dist-info/licenses/LICENSE
promptscope-0.1.1.dist-info/RECORD
