Metadata-Version: 2.4
Name: promptscope
Version: 0.1.1
Summary: Effortless Observability for LLM Prompts. Version, diff, replay, export, and guard costs with ease.
License: MIT
License-File: LICENSE
Author: PromptScope Dev
Author-email: hello@promptscope.dev
Requires-Python: >=3.8
Classifier: License :: OSI Approved :: MIT License
Classifier: Programming Language :: Python :: 3
Classifier: Programming Language :: Python :: 3.8
Classifier: Programming Language :: Python :: 3.9
Classifier: Programming Language :: Python :: 3.10
Classifier: Programming Language :: Python :: 3.11
Classifier: Programming Language :: Python :: 3.12
Classifier: Programming Language :: Python :: 3.13
Classifier: Programming Language :: Python :: 3.14
Requires-Dist: openai (>=1.0,<2.0)
Requires-Dist: pydantic (>=2.6,<3.0)
Requires-Dist: pydantic-settings (>=2.2,<3.0)
Requires-Dist: requests (>=2.31,<3.0)
Project-URL: Bug Tracker, https://github.com/promptscope-dev/promptscope/issues
Project-URL: Changelog, https://github.com/promptscope-dev/promptscope/releases
Project-URL: Documentation, https://github.com/promptscope-dev/promptscope/blob/main/README.md
Project-URL: Homepage, https://github.com/promptscope-dev/promptscope
Project-URL: Repository, https://github.com/promptscope-dev/promptscope
